bank_sync/__init__.py
bank_sync/admin.py
bank_sync/apps.py
bank_sync/models.py
bank_sync/tests.py
bank_sync/APIs/__init__.py
bank_sync/APIs/api_format.py
bank_sync/APIs/utils/__init__.py
bank_sync/APIs/utils/generate_code.py
bank_sync/Nash/__init__.py
bank_sync/Nash/nash.py
bank_sync/Resources/__init__.py
bank_sync/Resources/accounts.py
bank_sync/Resources/banks.py
bank_sync/Resources/helpers.py
bank_sync/Resources/operations.py
bank_sync/Resources/payments.py
bank_sync/Resources/resource.py
bank_sync/middlewares/__init__.py
bank_sync/middlewares/logs.py
bank_sync/migrations/0001_initial.py
bank_sync/migrations/0002_alter_callbacks_reference.py
bank_sync/migrations/0003_requestlogs.py
bank_sync/migrations/0004_requestlogs_error.py
bank_sync/migrations/0005_alter_requestlogs_error.py
bank_sync/migrations/0006_requestlogs_log_time.py
bank_sync/migrations/0007_responselogs.py
bank_sync/migrations/0008_responselogs_ip.py
bank_sync/migrations/0009_responselogs_error.py
bank_sync/migrations/0010_auto_20221117_1406.py
bank_sync/migrations/0011_ipndata.py
bank_sync/migrations/0012_alter_ipn_account_number.py
bank_sync/migrations/0013_alter_ipndata_ipn.py
bank_sync/migrations/0014_auto_20230125_1119.py
bank_sync/migrations/0015_auto_20230209_1410.py
bank_sync/migrations/0016_ipn_statement_url.py
bank_sync/migrations/0017_alter_ipn_statement_url.py
bank_sync/migrations/__init__.py
nashbanksync-0.1.85.dist-info/LICENSE
nashbanksync-0.1.85.dist-info/METADATA
nashbanksync-0.1.85.dist-info/WHEEL
nashbanksync-0.1.85.dist-info/top_level.txt
nashbanksync-0.1.85.dist-info/RECORD
