Metadata-Version: 2.1
Name: nashbanksync
Version: 0.1.85
Summary: Python library for connecting to the Nash Banks Framework
Home-page: https://github.com/NashInc/NashSync.git
Author: Dansol Obondo
Author-email: dansol@nashafrica.co
Classifier: Programming Language :: Python :: 3
Classifier: Programming Language :: Python :: 3.6
Classifier: Programming Language :: Python :: 3.7
Classifier: License :: OSI Approved :: MIT License
Classifier: Operating System :: OS Independent
License-File: LICENSE
